gdastudio/__init__.py
gdastudio/gdastudio.py
gdastudio-1.1.0.dist-info/LICENSE
gdastudio-1.1.0.dist-info/METADATA
gdastudio-1.1.0.dist-info/WHEEL
gdastudio-1.1.0.dist-info/top_level.txt
gdastudio-1.1.0.dist-info/RECORD
