Metadata-Version: 2.1
Name: gdastudio
Version: 1.1.0
Summary: ZALANDO GDA SQL Server, PGSQL,CSV & JSON Connection Objects and Tools
Author: Kamil Martenczuk
Author-email: <kamil.martenczuk.external@zalando.pl>
Maintainer: Damian Kłosowski
Maintainer-email: damian.klosowski.external@zalando.pl
Keywords: python,sql,csv,json
Classifier: Development Status :: 5 - Production/Stable
Classifier: Intended Audience :: Developers
Classifier: Programming Language :: Python :: 3
Classifier: Operating System :: Unix
Classifier: Operating System :: MacOS :: MacOS X
Classifier: Operating System :: Microsoft :: Windows
License-File: LICENSE
Requires-Dist: pypyodbc
Requires-Dist: tqdm
Requires-Dist: colorama
Requires-Dist: psycopg2-binary
